{
    "version": "124.61.1.50125-7299552",
    "homepage": "https://www.meetsidekick.com/",
    "description": "A work browser that is focused on productivity, speed, and security.",
    "license": {
        "identifier": "Freeware",
        "url": "https://www.meetsidekick.com/terms-of-use/"
    },
    "architecture": {
        "64bit": {
            "url": "https://cdn.meetsidekick.com/browser-builds/sidekick-win-release-x64-124.61.1.50125-7299552-default.exe#/dl.7z",
            "hash": "635ad25285ab5c324c9a10e5baaaf5e3e80af1d3d3eb67c14db642e7c58a1a40"
        }
    },
    "pre_install": "Expand-7zipArchive \"$dir\\sidekick.7z\" -ExtractDir 'Sidekick-bin' -Removal",
    "shortcuts": [
        [
            "sidekick.exe",
            "Sidekick Browser"
        ]
    ],
    "checkver": {
        "script": [
            "$redirUrl = [System.Net.HttpWebRequest]::Create('https://api.meetsidekick.com/downloads/df/win').GetResponse().ResponseUri.AbsoluteUri",
            "Write-Output $redirUrl"
        ],
        "regex": "sidekick-win-release-x64-([\\d.]+-[\\w]+)-default.exe"
    },
    "autoupdate": {
        "architecture": {
            "64bit": {
                "url": "https://cdn.meetsidekick.com/browser-builds/sidekick-win-release-x64-$version-default.exe#/dl.7z"
            }
        }
    }
}
